README.rst
fl_static.py
setup.py
fl_static.egg-info/PKG-INFO
fl_static.egg-info/SOURCES.txt
fl_static.egg-info/dependency_links.txt
fl_static.egg-info/not-zip-safe
fl_static.egg-info/requires.txt
fl_static.egg-info/top_level.txt