Metadata-Version: 1.1
Name: fl-static
Version: 0.0.2
Summary: Serve production static files with Flask.
Home-page: https://github.com/marksteve/fl-static
Author: Mark Steve Samson
Author-email: hello@marksteve.com
License: MIT
Platform: any
Classifier: Environment :: Web Environment
Classifier: Intended Audience :: Developers
Classifier: License :: OSI Approved :: MIT License
Classifier: Operating System :: OS Independent
Classifier: Programming Language :: Python
Classifier: Topic :: Internet :: WWW/HTTP :: Dynamic Content
Classifier: Topic :: Software Development :: Libraries :: Python Modules
